sparkproxy/__init__.py
sparkproxy/aes.py
sparkproxy/auth.py
sparkproxy/compat.py
sparkproxy/config.py
sparkproxy/rsa.py
sparkproxy/util.py
sparkproxy/http/__init__.py
sparkproxy/http/client.py
sparkproxy/http/response.py
sparkproxy/http/middleware/__init__.py
sparkproxy/http/middleware/base.py
sparkproxy/http/middleware/retry_domains.py
sparkproxy/http/middleware/ua.py
sparkproxy/services/__init__.py
sparkproxy/services/openapi/__init__.py
sparkproxy/services/openapi/client.py
sparkproxy-2.0.1.dist-info/LICENSE
sparkproxy-2.0.1.dist-info/METADATA
sparkproxy-2.0.1.dist-info/WHEEL
sparkproxy-2.0.1.dist-info/entry_points.txt
sparkproxy-2.0.1.dist-info/top_level.txt
sparkproxy-2.0.1.dist-info/RECORD
